{
  "db_name": "PostgreSQL",
  "query": "SELECT id, role AS \"role: String\", content, reasoning, created_at\n        FROM messages\n        WHERE conversation_id = $1\n        ORDER BY created_at ASC",
  "describe": {
    "columns": [
      {
        "ordinal": 0,
        "name": "id",
        "type_info": "Uuid"
      },
      {
        "ordinal": 1,
        "name": "role: String",
        "type_info": {
          "Custom": {
            "name": "message_role",
            "kind": {
              "Enum": [
                "user",
                "assistant"
              ]
            }
          }
        }
      },
      {
        "ordinal": 2,
        "name": "content",
        "type_info": "Text"
      },
      {
        "ordinal": 3,
        "name": "reasoning",
        "type_info": "Text"
      },
      {
        "ordinal": 4,
        "name": "created_at",
        "type_info": "Timestamptz"
      }
    ],
    "parameters": {
      "Left": [
        "Uuid"
      ]
    },
    "nullable": [
      false,
      false,
      false,
      true,
      true
    ]
  },
  "hash": "de76ea634dc9a38915ab571b17e6505a6774bba0fa8f87a3c1469adf0741252f"
}
